Metadata-Version: 2.1
Name: idlwrap
Version: 0.1.0
Summary: Provides an IDL-like interface to scipy/numpy for quick porting of IDL code to python.
Home-page: https://github.com/r4lv/idlwrap
Author: Ralf Farkas
Author-email: r4lv@peaxels.com
License: MIT
Platform: UNKNOWN
Classifier: License :: OSI Approved :: MIT License
Classifier: Operating System :: OS Independent
Classifier: Programming Language :: Python
Classifier: Programming Language :: Python :: 3
Classifier: Programming Language :: Python :: 3.5
Classifier: Programming Language :: Other
Classifier: Intended Audience :: Science/Research
Classifier: Topic :: Scientific/Engineering :: Physics
Classifier: Topic :: Scientific/Engineering :: Astronomy
Classifier: Topic :: Software Development :: Libraries
Requires-Python: >=3.5.0
